fastapi_simple_profiler/__init__.py
fastapi_simple_profiler/middleware.py
fastapi_simple_profiler/profiler_data.py
fastapi_simple_profiler-0.1.1.dist-info/licenses/LICENSE
fastapi_simple_profiler-0.1.1.dist-info/METADATA
fastapi_simple_profiler-0.1.1.dist-info/WHEEL
fastapi_simple_profiler-0.1.1.dist-info/top_level.txt
fastapi_simple_profiler-0.1.1.dist-info/RECORD
