Metadata-Version: 2.4
Name: fastapi-simple-profiler
Version: 0.1.1
Summary: A dead simple FastAPI profiler with CSV export for Google Sheets.
Home-page: https://github.com/jithinsankar/fastapi-simple-profiler
Author: Jithin Sankar
Project-URL: Bug Tracker, https://github.com/jithinsankar/fastapi-simple-profiler/issues
Project-URL: Source Code, https://github.com/jithinsankar/fastapi-simple-profiler
Keywords: fastapi profiler performance metrics csv google-sheets monitoring profiling
Classifier: Programming Language :: Python :: 3
Classifier: License :: OSI Approved :: MIT License
Classifier: Operating System :: OS Independent
Classifier: Framework :: FastAPI
Classifier: Topic :: Software Development :: Libraries :: Python Modules
Classifier: Topic :: System :: Monitoring
Classifier: Intended Audience :: Developers
Classifier: Development Status :: 3 - Alpha
Requires-Python: >=3.7
License-File: LICENSE
Requires-Dist: fastapi>=0.68.0
Requires-Dist: starlette>=0.14.2
Requires-Dist: pyinstrument>=4.0.0
Requires-Dist: pandas>=1.0.0
Dynamic: author
Dynamic: classifier
Dynamic: description
Dynamic: description-content-type
Dynamic: home-page
Dynamic: keywords
Dynamic: license-file
Dynamic: project-url
Dynamic: requires-dist
Dynamic: requires-python
Dynamic: summary
